autoballs/__init__.py
autoballs/helper.py
autoballs/ijconn.py
autoballs/utils.py
autoballs/network/__init__.py
autoballs/network/dataloader.py
autoballs/network/segment.py
autoballs-0.0.2.dist-info/LICENSE
autoballs-0.0.2.dist-info/METADATA
autoballs-0.0.2.dist-info/WHEEL
autoballs-0.0.2.dist-info/top_level.txt
autoballs-0.0.2.dist-info/RECORD
