Metadata-Version: 2.1
Name: autoballs
Version: 0.0.2
Summary: Python package for segmentation of axons and morphological analysis.
Home-page: UNKNOWN
Author: Ryan Greenhalgh
Author-email: ryan.greenhalgh@hotmail.co.uk, 
License: UNKNOWN
Platform: UNKNOWN
Classifier: Natural Language :: English
Classifier: Programming Language :: Python :: 3
Classifier: Programming Language :: Python
Requires-Dist: codecov (==2.1.11)
Requires-Dist: pytest (==6.2.2)
Requires-Dist: albumentations (==0.5.2)
Requires-Dist: attrs (==20.3.0)
Requires-Dist: certifi (==2020.12.5)
Requires-Dist: chardet (==4.0.0)
Requires-Dist: coverage (==5.5)
Requires-Dist: cycler (==0.10.0)
Requires-Dist: decorator (==4.4.2)
Requires-Dist: efficientnet-pytorch (==0.6.3)
Requires-Dist: idna (==2.10)
Requires-Dist: imageio (==2.9.0)
Requires-Dist: imgaug (==0.4.0)
Requires-Dist: imglyb (==1.0.0)
Requires-Dist: iniconfig (==1.1.1)
Requires-Dist: jgo (==1.0.0)
Requires-Dist: joblib (==1.0.1)
Requires-Dist: JPype1 (==1.2.1)
Requires-Dist: kiwisolver (==1.3.1)
Requires-Dist: matplotlib (==3.3.4)
Requires-Dist: munch (==2.5.0)
Requires-Dist: nd2reader (==3.2.3)
Requires-Dist: networkx (==2.5)
Requires-Dist: olefile (==0.46)
Requires-Dist: opencv-python (==4.5.1.48)
Requires-Dist: opencv-python-headless (==4.5.1.48)
Requires-Dist: packaging (==20.9)
Requires-Dist: pandas (==1.2.3)
Requires-Dist: patsy (==0.5.1)
Requires-Dist: Pillow (>=6.2.0)
Requires-Dist: PIMS (==0.5)
Requires-Dist: pluggy (==0.13.1)
Requires-Dist: pretrainedmodels (==0.7.4)
Requires-Dist: psutil (==5.8.0)
Requires-Dist: py (==1.10.0)
Requires-Dist: pyimagej (==1.0.0)
Requires-Dist: pyparsing (==2.4.7)
Requires-Dist: python-dateutil (==2.8.1)
Requires-Dist: pytz (==2021.1)
Requires-Dist: PyWavelets (==1.1.1)
Requires-Dist: PyYAML (==5.4.1)
Requires-Dist: requests (==2.25.1)
Requires-Dist: scikit-image (==0.18.1)
Requires-Dist: scikit-learn (==0.24.1)
Requires-Dist: scipy (==1.6.1)
Requires-Dist: scyjava (==1.1.0)
Requires-Dist: seaborn (==0.11.1)
Requires-Dist: segmentation-models-pytorch (==0.1.3)
Requires-Dist: Shapely (==1.7.1)
Requires-Dist: sklearn (==0.0)
Requires-Dist: slicerator (==1.0.0)
Requires-Dist: statsmodels (==0.12.2)
Requires-Dist: threadpoolctl (==2.1.0)
Requires-Dist: tifffile (==2021.2.26)
Requires-Dist: timm (==0.3.2)
Requires-Dist: toml (==0.10.2)
Requires-Dist: torch (==1.8.0)
Requires-Dist: torchaudio (==0.8.0)
Requires-Dist: torchvision (==0.9.0)
Requires-Dist: tqdm (==4.59.0)
Requires-Dist: urllib3 (==1.26.3)
Requires-Dist: xarray (==0.17.0)
Requires-Dist: xmltodict (==0.12.0)
